unilite/__init__.py
unilite/constants.py
unilite/contract_maker.py
unilite/w3.py
unione-0.5.dist-info/METADATA
unione-0.5.dist-info/WHEEL
unione-0.5.dist-info/top_level.txt
unione-0.5.dist-info/RECORD
