Metadata-Version: 2.1
Name: unione
Version: 0.5
Requires-Dist: web3
